duckduckgo_mcp/__init__.py
duckduckgo_mcp/__main__.py
duckduckgo_mcp/_version.py
duckduckgo_mcp/cli.py
duckduckgo_mcp/duckduckgo_search.py
duckduckgo_mcp/jina_fetch.py
duckduckgo_mcp/server.py
duckduckgo_mcp-2.1.0.dist-info/licenses/LICENSE
duckduckgo_mcp-2.1.0.dist-info/METADATA
duckduckgo_mcp-2.1.0.dist-info/WHEEL
duckduckgo_mcp-2.1.0.dist-info/entry_points.txt
duckduckgo_mcp-2.1.0.dist-info/top_level.txt
duckduckgo_mcp-2.1.0.dist-info/RECORD
