Metadata-Version: 2.4
Name: duckduckgo-mcp
Version: 2.1.0
Summary: DuckDuckGo search and content retrieval tool for MCP (Model Context Protocol)
Author-email: Eddie Pick <eddie@pick.fr>
License: MIT
Project-URL: Homepage, https://github.com/CyranoB/duckduckgo-mcp
Project-URL: Repository, https://github.com/CyranoB/duckduckgo-mcp
Project-URL: Issues, https://github.com/CyranoB/duckduckgo-mcp/issues
Classifier: Development Status :: 3 - Alpha
Classifier: Intended Audience :: Developers
Classifier: Programming Language :: Python :: 3
Classifier: Programming Language :: Python :: 3.10
Classifier: Programming Language :: Python :: 3.11
Classifier: Programming Language :: Python :: 3.12
Classifier: Topic :: Software Development :: Libraries :: Python Modules
Classifier: Topic :: Internet :: WWW/HTTP :: Indexing/Search
Requires-Python: >=3.10
License-File: LICENSE
Requires-Dist: mcp>=1.9.0
Requires-Dist: fastmcp>=2.3.4
Requires-Dist: requests<2.32.0,>=2.28.0
Requires-Dist: urllib3<2.0.0,>=1.26.0
Requires-Dist: beautifulsoup4>=4.11.0
Requires-Dist: ddgs>=9.5.2
Provides-Extra: dev
Requires-Dist: pytest>=7.0.0; extra == "dev"
Requires-Dist: black>=23.0.0; extra == "dev"
Requires-Dist: isort>=5.0.0; extra == "dev"
Requires-Dist: mypy>=1.0.0; extra == "dev"
Requires-Dist: pytest-cov>=4.0.0; extra == "dev"
Dynamic: license-file
